qlatent/__init__.py
qlatent/utils.py
qlatent/qabstract/__init__.py
qlatent/qabstract/qabstract.py
qlatent/qabstract/qabstract_torch.py
qlatent/qcola/__init__.py
qlatent/qcola/qcola.py
qlatent/qmlm/__init__.py
qlatent/qmlm/qmlm.py
qlatent/qmnli/__init__.py
qlatent/qmnli/qmnli.py
qlatent/qmnli/qmnli_torch.py
qlatent/qmnli/utils.py
qlatent/qnsp/__init__.py
qlatent/qnsp/qnsp.py
qlatent/questionnaire_eval/__init__.py
qlatent/questionnaire_eval/questionnaire_utils.py
qlatent-1.0.22.data/data/Academic Article/2409.19655v1.pdf
qlatent-1.0.22.dist-info/licenses/LICENSE-CC-BY-SA
qlatent-1.0.22.dist-info/METADATA
qlatent-1.0.22.dist-info/WHEEL
qlatent-1.0.22.dist-info/top_level.txt
qlatent-1.0.22.dist-info/RECORD
