Metadata-Version: 2.4
Name: qlatent
Version: 1.0.22
Summary: A Python package for running psychometric on LLMs.
Classifier: Programming Language :: Python :: 3
Classifier: License :: OSI Approved :: Apache Software License
Classifier: Operating System :: OS Independent
Requires-Python: >=3.8
License-File: LICENSE-CC-BY-SA
Requires-Dist: numpy
Requires-Dist: pandas
Requires-Dist: seaborn
Requires-Dist: scipy
Requires-Dist: scikit-learn
Requires-Dist: transformers
Requires-Dist: pingouin
Requires-Dist: typeguard
Requires-Dist: datasets
Requires-Dist: evaluate
Requires-Dist: matplotlib
Requires-Dist: sentence_transformers
Dynamic: classifier
Dynamic: description
Dynamic: description-content-type
Dynamic: license-file
Dynamic: requires-dist
Dynamic: requires-python
Dynamic: summary
